Workbook

Sheet Data Dictionary
A4: Sheet Name | B4: Column Name | C4: Meaning
A5: GDP | B5: Region | C5: Region
A6: GDP | B6: Country/Region | C6: Country - Region
A7: GDP | B7: Year | C7: Year of measurement
A8: GDP | B8: GDP | C8: Gross domestic product (in USD)
A9: GDP | B9: Health Exp % GDP | C9: Health expenditure as a % of GDP ( Health Exp/Capita is more imp)
A10: GDP | B10: Health Exp/Capita | C10: Health expenditure per capita (In USD)
A11: GDP | B11: Lending Interest | C11: Lending interest rate
A12: ENERGY | B12: Energy Usage | C12: Energy usage n KWh
A13: ENERGY | B13: CO2 Emissions | C13: Carbon dioxide emission in CO2e
A14: HUMAN RESOURCES | B14: Birth Rate | C14: Rate at which new births are taking place
A15: HUMAN RESOURCES | B15: Infant Mortality Rate | C15: % of infants that die before the age of 5 years
... A30: BUSINESS | B30: Mobile Phone Usage | C30: Percentage of population using mobile phone

Sheet GDP_sheet
A1: Important Column | B1: GDP | C1: Health Exp/Capita | D1: Lending Interest | E1: Country/Region | F1: YEAR | G1: Region | H1: Energy Usage | I1: CO2 Emissions | J1: Birth Rate | K1: Infant Mortality Rate | L1: Life Expectancy Female | M1: Life Expectancy Male | N1: Population 0-14 | O1: Population 15-64 | P1: Population 65+ | Q1: Population Total | R1: Population Urban | S1: Tourism Inbound | T1: Tourism Outbound | U1: Business Tax Rate | V1: Internet Usage | W1: Mobile Phone Usage | X1: GDP/Capita | Y1: CO2 emission/Capita | Z1: Energy consumption/capita | AA1: Tourism outbound/capita
A2: Afghanistan-Asia|2000 | B2: 1.5079753e+10 | C2: 193 | D2: 0.12 | E2: Afghanistan-Asia | F2: 2000 | G2: Asia | H2: {=VLOOKUP(A2,ENERGY!$A$2:$C$2692,{2,3},0)} -> 14338 | I2: 8529 | J2: {=VLOOKUP(A2,HUMANRESOURCES!$A$2:$J$2692,{2,3,4,5,6,7,8,9,10},0)} -> 0.05 | K2: 0.095 | L2: 56 | M2: 54 | N2: 0.495 | O2: 0.485 | P2: 0.02 | Q2: 20595360 | R2: 0.213 | S2: {=VLOOKUP(A2,TOURISM!$A$2:$C$2692,{2,3},0)} -> 680000000 | T2: 448000000 | U2: {=VLOOKUP(A2,BUSINESS!$A$2:$D$2692,{2,3,4},0)} -> 0.48966901 | V2: 0.129 | W2: 0.57976412 | X2: =B2/Q2 -> 732.19174 | Y2: =I2/Q2 -> 0.0004141224 | Z2: =H2/Q2 -> 0.00069617623 | AA2: =T2/Q2 -> 21.752472
A3: Afghanistan-Asia|2001 | B3: 2461666315 | C3: 193 | D3: 0.12 | E3: Afghanistan-Asia | F3: 2001 | G3: Asia | H3: {=VLOOKUP(A3,ENERGY!$A$2:$C$2692,{2,3},0)} -> 14338 | I3: 8529 | J3: {=VLOOKUP(A3,HUMANRESOURCES!$A$2:$J$2692,{2,3,4,5,6,7,8,9,10},0)} -> 0.049 | K3: 0.093 | L3: 56 | M3: 54 | N3: 0.495 | O3: 0.484 | P3: 0.02 | Q3: 21347782 | R3: 0.216 | S3: {=VLOOKUP(A3,TOURISM!$A$2:$C$2692,{2,3},0)} -> 680000000 | T3: 448000000 | U3: {=VLOOKUP(A3,BUSINESS!$A$2:$D$2692,{2,3,4},0)} -> 0.48966901 | V3: 0 | W3: 0.57976412 | X3: =B3/Q3 -> 115.31251 | Y3: =I3/Q3 -> 0.00039952628 | Z3: =H3/Q3 -> 0.00067163886 | AA3: =T3/Q3 -> 20.985787
A4: Afghanistan-Asia|2002 | B4: 4128818043 | C4: 14 | D4: 0.12 | E4: Afghanistan-Asia | F4: 2002 | G4: Asia | H4: {=VLOOKUP(A4,ENERGY!$A$2:$C$2692,{2,3},0)} -> 14338 | I4: 8236 | J4: {=VLOOKUP(A4,HUMANRESOURCES!$A$2:$J$2692,{2,3,4,5,6,7,8,9,10},0)} -> 0.048 | K4: 0.091 | L4: 57 | M4: 55 | N4: 0.495 | O4: 0.485 | P4: 0.02 | Q4: 22202806 | R4: 0.219 | S4: {=VLOOKUP(A4,TOURISM!$A$2:$C$2692,{2,3},0)} -> 680000000 | T4: 448000000 | U4: {=VLOOKUP(A4,BUSINESS!$A$2:$D$2692,{2,3,4},0)} -> 0.48966901 | V4: 0 | W4: 0.001 | X4: =B4/Q4 -> 185.95929 | Y4: =I4/Q4 -> 0.0003709441 | Z4: =H4/Q4 -> 0.00064577423 | AA4: =T4/Q4 -> 20.17763
A5: Afghanistan-Asia|2003 | B5: 4583648922 | C5: 18 | D5: 0.12 | E5: Afghanistan-Asia | F5: 2003 | G5: Asia | H5: {=VLOOKUP(A5,ENERGY!$A$2:$C$2692,{2,3},0)} -> 14338 | I5: 6524 | J5: {=VLOOKUP(A5,HUMANRESOURCES!$A$2:$J$2692,{2,3,4,5,6,7,8,9,10},0)} -> 0.047 | K5: 0.088 | L5: 57 | M5: 55 | N5: 0.494 | O5: 0.485 | P5: 0.02 | Q5: 23116142 | R5: 0.222 | S5: {=VLOOKUP(A5,TOURISM!$A$2:$C$2692,{2,3},0)} -> 680000000 | T5: 448000000 | U5: {=VLOOKUP(A5,BUSINESS!$A$2:$D$2692,{2,3,4},0)} -> 0.48966901 | V5: 0.001 | W5: 0.009 | X5: =B5/Q5 -> 198.2878 | Y5: =I5/Q5 -> 0.00028222703 | Z5: =H5/Q5 -> 0.00062025921 | AA5: =T5/Q5 -> 19.380397
A6: Afghanistan-Asia|2004 | B6: 5285461999 | C6: 19 | D6: 0.12 | E6: Afghanistan-Asia | F6: 2004 | G6: Asia | H6: {=VLOOKUP(A6,ENERGY!$A$2:$C$2692,{2,3},0)} -> 14338 | I6: 3927 | J6: {=VLOOKUP(A6,HUMANRESOURCES!$A$2:$J$2692,{2,3,4,5,6,7,8,9,10},0)} -> 0.046 | K6: 0.086 | L6: 58 | M6: 55 | N6: 0.494 | O6: 0.486 | P6: 0.02 | Q6: 24018682 | R6: 0.226 | S6: {=VLOOKUP(A6,TOURISM!$A$2:$C$2692,{2,3},0)} -> 680000000 | T6: 448000000 | U6: {=VLOOKUP(A6,BUSINESS!$A$2:$D$2692,{2,3,4},0)} -> 0.48966901 | V6: 0.001 | W6: 0.025 | X6: =B6/Q6 -> 220.05629 | Y6: =I6/Q6 -> 0.00016349773 | Z6: =H6/Q6 -> 0.00059695199 | AA6: =T6/Q6 -> 18.652148
A7: Afghanistan-Asia|2005 | B7: 6275076016 | C7: 21 | D7: 0.12 | E7: Afghanistan-Asia | F7: 2005 | G7: Asia | H7: {=VLOOKUP(A7,ENERGY!$A$2:$C$2692,{2,3},0)} -> 14338 | I7: 1991 | J7: {=VLOOKUP(A7,HUMANRESOURCES!$A$2:$J$2692,{2,3,4,5,6,7,8,9,10},0)} -> 0.045 | K7: 0.084 | L7: 58 | M7: 56 | N7: 0.493 | O7: 0.487 | P7: 0.02 | Q7: 24860855 | R7: 0.229 | S7: {=VLOOKUP(A7,TOURISM!$A$2:$C$2692,{2,3},0)} -> 680000000 | T7: 448000000 | U7: {=VLOOKUP(A7,BUSINESS!$A$2:$D$2692,{2,3,4},0)} -> 0.363 | V7: 0.012 | W7: 0.048 | X7: =B7/Q7 -> 252.40789 | Y7: =I7/Q7 -> 8.0085741e-05 | Z7: =H7/Q7 -> 0.00057672996 | AA7: =T7/Q7 -> 18.020297
A8: Afghanistan-Asia|2006 | B8: 7057597615 | C8: 23 | D8: 0.18 | E8: Afghanistan-Asia | F8: 2006 | G8: Asia | H8: {=VLOOKUP(A8,ENERGY!$A$2:$C$2692,{2,3},0)} -> 14338 | I8: 1016 | J8: {=VLOOKUP(A8,HUMANRESOURCES!$A$2:$J$2692,{2,3,4,5,6,7,8,9,10},0)} -> 0.044 | K8: 0.082 | L8: 59 | M8: 56 | N8: 0.493 | O8: 0.487 | P8: 0.02 | Q8: 25631282 | R8: 0.232 | S8: {=VLOOKUP(A8,TOURISM!$A$2:$C$2692,{2,3},0)} -> 680000000 | T8: 448000000 | U8: {=VLOOKUP(A8,BUSINESS!$A$2:$D$2692,{2,3,4},0)} -> 0.363 | V8: 0.021 | W8: 0.098 | X8: =B8/Q8 -> 275.35094 | Y8: =I8/Q8 -> 3.9639063e-05 | Z8: =H8/Q8 -> 0.00055939457 | AA8: =T8/Q8 -> 17.478642
A9: Afghanistan-Asia|2007 | B9: 9843851009 | C9: 30 | D9: 0.181 | E9: Afghanistan-Asia | F9: 2007 | G9: Asia | H9: {=VLOOKUP(A9,ENERGY!$A$2:$C$2692,{2,3},0)} -> 14338 | I9: 583 | J9: {=VLOOKUP(A9,HUMANRESOURCES!$A$2:$J$2692,{2,3,4,5,6,7,8,9,10},0)} -> 0.042 | K9: 0.08 | L9: 59 | M9: 57 | N9: 0.492 | O9: 0.487 | P9: 0.021 | Q9: 26349243 | R9: 0.236 | S9: {=VLOOKUP(A9,TOURISM!$A$2:$C$2692,{2,3},0)} -> 680000000 | T9: 448000000 | U9: {=VLOOKUP(A9,BUSINESS!$A$2:$D$2692,{2,3,4},0)} -> 0.363 | V9: 0.019 | W9: 0.177 | X9: =B9/Q9 -> 373.59142 | Y9: =I9/Q9 -> 2.2125873e-05 | Z9: =H9/Q9 -> 0.00054415226 | AA9: =T9/Q9 -> 17.002386
A10: Afghanistan-Asia|2008 | B10: 10190534636 | C10: 35 | D10: 0.149 | E10: Afghanistan-Asia | F10: 2008 | G10: Asia | H10: {=VLOOKUP(A10,ENERGY!$A$2:$C$2692,{2,3},0)} -> 14338 | I10: 781 | J10: {=VLOOKUP(A10,HUMANRESOURCES!$A$2:$J$2692,{2,3,4,5,6,7,8,9,10},0)} -> 0.041 | K10: 0.079 | L10: 60 | M10: 57 | N10: 0.492 | O10: 0.487 | P10: 0.021 | Q10: 27032197 | R10: 0.239 | S10: {=VLOOKUP(A10,TOURISM!$A$2:$C$2692,{2,3},0)} -> 43000000 | T10: 58000000 | U10: {=VLOOKUP(A10,BUSINESS!$A$2:$D$2692,{2,3,4},0)} -> 0.363 | V10: 0.018 | W10: 0.292 | X10: =B10/Q10 -> 376.97767 | Y10: =I10/Q10 -> 2.8891473e-05 | Z10: =H10/Q10 -> 0.00053040454 | AA10: =T10/Q10 -> 2.1455896
A11: Afghanistan-Asia|2009 | B11: 12486950469 | C11: 35 | D11: 0.15 | E11: Afghanistan-Asia | F11: 2009 | G11: Asia | H11: {=VLOOKUP(A11,ENERGY!$A$2:$C$2692,{2,3},0)} -> 14338 | I11: 1338 | J11: {=VLOOKUP(A11,HUMANRESOURCES!$A$2:$J$2692,{2,3,4,5,6,7,8,9,10},0)} -> 0.039 | K11: 0.077 | L11: 60 | M11: 58 | N11: 0.49 | O11: 0.489 | P11: 0.021 | Q11: 27708187 | R11: 0.243 | S11: {=VLOOKUP(A11,TOURISM!$A$2:$C$2692,{2,3},0)} -> 96000000 | T11: 61000000 | U11: {=VLOOKUP(A11,BUSINESS!$A$2:$D$2692,{2,3,4},0)} -> 0.363 | V11: 0.036 | W11: 0.379 | X11: =B11/Q11 -> 450.65924 | Y11: =I11/Q11 -> 4.8288977e-05 | Z11: =H11/Q11 -> 0.00051746439 | AA11: =T11/Q11 -> 2.2015154
A12: Afghanistan-Asia|2010 | B12: 15936784436 | C12: 43 | D12: 0.157 | E12: Afghanistan-Asia | F12: 2010 | G12: Asia | H12: {=VLOOKUP(A12,ENERGY!$A$2:$C$2692,{2,3},0)} -> 14338 | I12: 733 | J12: {=VLOOKUP(A12,HUMANRESOURCES!$A$2:$J$2692,{2,3,4,5,6,7,8,9,10},0)} -> 0.038 | K12: 0.075 | L12: 61 | M12: 58 | N12: 0.486 | O12: 0.492 | P12: 0.022 | Q12: 28397812 | R12: 0.247 | S12: {=VLOOKUP(A12,TOURISM!$A$2:$C$2692,{2,3},0)} -> 138000000 | T12: 86000000 | U12: {=VLOOKUP(A12,BUSINESS!$A$2:$D$2692,{2,3,4},0)} -> 0.363 | V12: 0.04 | W12: 0.458 | X12: =B12/Q12 -> 561.19762 | Y12: =I12/Q12 -> 2.5811848e-05 | Z12: =H12/Q12 -> 0.00050489805 | AA12: =T12/Q12 -> 3.0284023
A13: Afghanistan-Asia|2011 | B13: 17870159082 | C13: 48 | D13: 0.151 | E13: Afghanistan-Asia | F13: 2011 | G13: Asia | H13: {=VLOOKUP(A13,ENERGY!$A$2:$C$2692,{2,3},0)} -> 14338 | I13: 645 | J13: {=VLOOKUP(A13,HUMANRESOURCES!$A$2:$J$2692,{2,3,4,5,6,7,8,9,10},0)} -> 0.037 | K13: 0.074 | L13: 61 | M13: 59 | N13: 0.481 | O13: 0.497 | P13: 0.022 | Q13: 29105480 | R13: 0.251 | S13: {=VLOOKUP(A13,TOURISM!$A$2:$C$2692,{2,3},0)} -> 137000000 | T13: 127000000 | U13: {=VLOOKUP(A13,BUSINESS!$A$2:$D$2692,{2,3,4},0)} -> 0.363 | V13: 0.05 | W13: 0.603 | X13: =B13/Q13 -> 613.97919 | Y13: =I13/Q13 -> 2.2160775e-05 | Z13: =H13/Q13 -> 0.00049262201 | AA13: =T13/Q13 -> 4.3634395
... A2692: Zimbabwe-Africa|2012 | B2692: 12472416688 | C2692: 193 | D2692: 0.12 | E2692: Zimbabwe-Africa | F2692: 2012 | G2692: Africa | H2692: {=VLOOKUP(A2692,ENERGY!$A$2:$C$2692,{2,3},0)} -> 9865 | I2692: 13887 | J2692: {=VLOOKUP(A2692,HUMANRESOURCES!$A$2:$J$2692,{2,3,4,5,6,7,8,9,10},0)} -> 0.032 | K2692: 0.055 | L2692: 59 | M2692: 57 | N2692: 0.402 | O2692: 0.558 | P2692: 0.039 | Q2692: 13724317 | R2692: 0.328 | S2692: {=VLOOKUP(A2692,TOURISM!$A$2:$C$2692,{2,3},0)} -> 749000000 | T2692: 448000000 | U2692: {=VLOOKUP(A2692,BUSINESS!$A$2:$D$2692,{2,3,4},0)} -> 0.345 | V2692: 0.171 | W2692: 0.919 | X2692: =B2692/Q2692 -> 908.78232 | Y2692: =I2692/Q2692 -> 0.0010118536 | Z2692: =H2692/Q2692 -> 0.00071879715 | AA2692: =T2692/Q2692 -> 32.64279

Sheet ENERGY
A1: Important Column | B1: Energy Usage | C1: CO2 Emissions
A2: Afghanistan-Asia|2000 | B2: 14338 | C2: 8529
A3: Afghanistan-Asia|2001 | B3: 14338 | C3: 8529
A4: Afghanistan-Asia|2002 | B4: 14338 | C4: 8236
A5: Afghanistan-Asia|2003 | B5: 14338 | C5: 6524
A6: Afghanistan-Asia|2004 | B6: 14338 | C6: 3927
A7: Afghanistan-Asia|2005 | B7: 14338 | C7: 1991
A8: Afghanistan-Asia|2006 | B8: 14338 | C8: 1016
A9: Afghanistan-Asia|2007 | B9: 14338 | C9: 583
A10: Afghanistan-Asia|2008 | B10: 14338 | C10: 781
A11: Afghanistan-Asia|2009 | B11: 14338 | C11: 1338
A12: Afghanistan-Asia|2010 | B12: 14338 | C12: 733
A13: Afghanistan-Asia|2011 | B13: 14338 | C13: 645
... A2692: Zimbabwe-Africa|2012 | B2692: 9865 | C2692: 13887

Sheet HUMANRESOURCES
A1: Important Column | B1: Birth Rate | C1: Infant Mortality Rate | D1: Life Expectancy Female | E1: Life Expectancy Male | F1: Population 0-14 | G1: Population 15-64 | H1: Population 65+ | I1: Population Total | J1: Population Urban
A2: Afghanistan-Asia|2000 | B2: 0.05 | C2: 0.095 | D2: 56 | E2: 54 | F2: 0.495 | G2: 0.485 | H2: 0.02 | I2: 20595360 | J2: 0.213
A3: Afghanistan-Asia|2001 | B3: 0.049 | C3: 0.093 | D3: 56 | E3: 54 | F3: 0.495 | G3: 0.484 | H3: 0.02 | I3: 21347782 | J3: 0.216
A4: Afghanistan-Asia|2002 | B4: 0.048 | C4: 0.091 | D4: 57 | E4: 55 | F4: 0.495 | G4: 0.485 | H4: 0.02 | I4: 22202806 | J4: 0.219
A5: Afghanistan-Asia|2003 | B5: 0.047 | C5: 0.088 | D5: 57 | E5: 55 | F5: 0.494 | G5: 0.485 | H5: 0.02 | I5: 23116142 | J5: 0.222
A6: Afghanistan-Asia|2004 | B6: 0.046 | C6: 0.086 | D6: 58 | E6: 55 | F6: 0.494 | G6: 0.486 | H6: 0.02 | I6: 24018682 | J6: 0.226
A7: Afghanistan-Asia|2005 | B7: 0.045 | C7: 0.084 | D7: 58 | E7: 56 | F7: 0.493 | G7: 0.487 | H7: 0.02 | I7: 24860855 | J7: 0.229
A8: Afghanistan-Asia|2006 | B8: 0.044 | C8: 0.082 | D8: 59 | E8: 56 | F8: 0.493 | G8: 0.487 | H8: 0.02 | I8: 25631282 | J8: 0.232
A9: Afghanistan-Asia|2007 | B9: 0.042 | C9: 0.08 | D9: 59 | E9: 57 | F9: 0.492 | G9: 0.487 | H9: 0.021 | I9: 26349243 | J9: 0.236
A10: Afghanistan-Asia|2008 | B10: 0.041 | C10: 0.079 | D10: 60 | E10: 57 | F10: 0.492 | G10: 0.487 | H10: 0.021 | I10: 27032197 | J10: 0.239
A11: Afghanistan-Asia|2009 | B11: 0.039 | C11: 0.077 | D11: 60 | E11: 58 | F11: 0.49 | G11: 0.489 | H11: 0.021 | I11: 27708187 | J11: 0.243
A12: Afghanistan-Asia|2010 | B12: 0.038 | C12: 0.075 | D12: 61 | E12: 58 | F12: 0.486 | G12: 0.492 | H12: 0.022 | I12: 28397812 | J12: 0.247
A13: Afghanistan-Asia|2011 | B13: 0.037 | C13: 0.074 | D13: 61 | E13: 59 | F13: 0.481 | G13: 0.497 | H13: 0.022 | I13: 29105480 | J13: 0.251
... A2674: Zambia-Africa|2007 | B2674: 0.044 | C2674: 0.07 | D2674: 51 | E2674: 49 | F2674: 0.469 | G2674: 0.504 | H2674: 0.027 | I2674: 12109620 | J2674: 0.375
A2675: Zambia-Africa|2008 | B2675: 0.043 | C2675: 0.067 | D2675: 52 | E2675: 51 | F2675: 0.47 | G2675: 0.504 | H2675: 0.027 | I2675: 12456527 | J2675: 0.379 | K2675: =TYPE(J2) -> 1
A2676: Zambia-Africa|2009 | B2676: 0.043 | C2676: 0.065 | D2676: 54 | E2676: 52 | F2676: 0.47 | G2676: 0.504 | H2676: 0.027 | I2676: 12825031 | J2676: 0.383
A2677: Zambia-Africa|2010 | B2677: 0.043 | C2677: 0.064 | D2677: 56 | E2677: 53 | F2677: 0.469 | G2677: 0.504 | H2677: 0.027 | I2677: 13216985 | J2677: 0.387
A2678: Zambia-Africa|2011 | B2678: 0.043 | C2678: 0.059 | D2678: 57 | E2678: 54 | F2678: 0.468 | G2678: 0.505 | H2678: 0.026 | I2678: 13633796 | J2678: 0.392
A2679: Zambia-Africa|2012 | B2679: 0.043 | C2679: 0.057 | D2679: 59 | E2679: 55 | F2679: 0.467 | G2679: 0.506 | H2679: 0.026 | I2679: 14075099 | J2679: 0.396
A2680: Zimbabwe-Africa|2000 | B2680: 0.032 | C2680: 0.061 | D2680: 44 | E2680: 44 | F2680: 0.422 | G2680: 0.545 | H2680: 0.034 | I2680: 12503652 | J2680: 0.338
A2681: Zimbabwe-Africa|2001 | B2681: 0.032 | C2681: 0.06 | D2681: 43 | E2681: 43 | F2681: 0.419 | G2681: 0.547 | H2681: 0.034 | I2681: 12586763 | J2681: 0.342
A2682: Zimbabwe-Africa|2002 | B2682: 0.032 | C2682: 0.059 | D2682: 43 | E2682: 43 | F2682: 0.417 | G2682: 0.548 | H2682: 0.035 | I2682: 12640922 | J2682: 0.346
A2683: Zimbabwe-Africa|2003 | B2683: 0.032 | C2683: 0.058 | D2683: 42 | E2683: 43 | F2683: 0.416 | G2683: 0.549 | H2683: 0.035 | I2683: 12673103 | J2683: 0.345
A2684: Zimbabwe-Africa|2004 | B2684: 0.032 | C2684: 0.058 | D2684: 43 | E2684: 44 | F2684: 0.415 | G2684: 0.549 | H2684: 0.036 | I2684: 12693047 | J2684: 0.343
A2685: Zimbabwe-Africa|2005 | B2685: 0.032 | C2685: 0.057 | D2685: 43 | E2685: 44 | F2685: 0.415 | G2685: 0.548 | H2685: 0.037 | I2685: 12710589 | J2685: 0.341
A2686: Zimbabwe-Africa|2006 | B2686: 0.032 | C2686: 0.057 | D2686: 44 | E2686: 46 | F2686: 0.415 | G2686: 0.548 | H2686: 0.038 | I2686: 12724308 | J2686: 0.339
A2687: Zimbabwe-Africa|2007 | B2687: 0.032 | C2687: 0.058 | D2687: 46 | E2687: 47 | F2687: 0.415 | G2687: 0.546 | H2687: 0.038 | I2687: 12740160 | J2687: 0.337
... A2692: Zimbabwe-Africa|2012 | B2692: 0.032 | C2692: 0.055 | D2692: 59 | E2692: 57 | F2692: 0.402 | G2692: 0.558 | H2692: 0.039 | I2692: 13724317 | J2692: 0.328

Sheet TOURISM
A1: Important Column | B1: Tourism Inbound | C1: Tourism Outbound | D1: Type
A2: Afghanistan-Asia|2000 | B2: 680000000 | C2: 448000000 | D2: =TYPE(C2) -> 1
A3: Afghanistan-Asia|2001 | B3: 680000000 | C3: 448000000
A4: Afghanistan-Asia|2002 | B4: 680000000 | C4: 448000000
A5: Afghanistan-Asia|2003 | B5: 680000000 | C5: 448000000
A6: Afghanistan-Asia|2004 | B6: 680000000 | C6: 448000000
A7: Afghanistan-Asia|2005 | B7: 680000000 | C7: 448000000
A8: Afghanistan-Asia|2006 | B8: 680000000 | C8: 448000000
A9: Afghanistan-Asia|2007 | B9: 680000000 | C9: 448000000
A10: Afghanistan-Asia|2008 | B10: 43000000 | C10: 58000000
A11: Afghanistan-Asia|2009 | B11: 96000000 | C11: 61000000
A12: Afghanistan-Asia|2010 | B12: 138000000 | C12: 86000000
A13: Afghanistan-Asia|2011 | B13: 137000000 | C13: 127000000
A14: Afghanistan-Asia|2012 | B14: 116000000 | C14: 80000000
... A2692: Zimbabwe-Africa|2012 | B2692: 749000000 | C2692: 448000000

Sheet BUSINESS
A1: Important Column | B1: Business Tax Rate | C1: Internet Usage | D1: Mobile Phone Usage
A2: Afghanistan-Asia|2000 | B2: 0.48966901 | C2: 0.129 | D2: 0.57976412 | E2: =TYPE(D2) -> 1
A3: Afghanistan-Asia|2001 | B3: 0.48966901 | C3: 0 | D3: 0.57976412
A4: Afghanistan-Asia|2002 | B4: 0.48966901 | C4: 0 | D4: 0.001
A5: Afghanistan-Asia|2003 | B5: 0.48966901 | C5: 0.001 | D5: 0.009
A6: Afghanistan-Asia|2004 | B6: 0.48966901 | C6: 0.001 | D6: 0.025
A7: Afghanistan-Asia|2005 | B7: 0.363 | C7: 0.012 | D7: 0.048
A8: Afghanistan-Asia|2006 | B8: 0.363 | C8: 0.021 | D8: 0.098
A9: Afghanistan-Asia|2007 | B9: 0.363 | C9: 0.019 | D9: 0.177
A10: Afghanistan-Asia|2008 | B10: 0.363 | C10: 0.018 | D10: 0.292
A11: Afghanistan-Asia|2009 | B11: 0.363 | C11: 0.036 | D11: 0.379
A12: Afghanistan-Asia|2010 | B12: 0.363 | C12: 0.04 | D12: 0.458
A13: Afghanistan-Asia|2011 | B13: 0.363 | C13: 0.05 | D13: 0.603
A14: Afghanistan-Asia|2012 | B14: 0.363 | C14: 0.055 | D14: 0.655
... A2692: Zimbabwe-Africa|2012 | B2692: 0.345 | C2692: 0.171 | D2692: 0.919
